pyqt_ext/__init__.py
pyqt_ext/pyqtgraph_ext/AxisRegion.py
pyqt_ext/pyqtgraph_ext/Figure.py
pyqt_ext/pyqtgraph_ext/Graph.py
pyqt_ext/pyqtgraph_ext/GraphStyle.py
pyqt_ext/pyqtgraph_ext/Plot.py
pyqt_ext/pyqtgraph_ext/PlotGrid.py
pyqt_ext/pyqtgraph_ext/View.py
pyqt_ext/pyqtgraph_ext/__init__.py
pyqt_ext/tmp/Chart.py
pyqt_ext/tree/AbstractTreeItem.py
pyqt_ext/tree/AbstractTreeModel.py
pyqt_ext/tree/KeyValueTreeItem.py
pyqt_ext/tree/KeyValueTreeModel.py
pyqt_ext/tree/KeyValueTreeView.py
pyqt_ext/tree/TreeView.py
pyqt_ext/tree/__init__.py
pyqt_ext/utils/Color.py
pyqt_ext/utils/__init__.py
pyqt_ext/widgets/CollapsibleSection.py
pyqt_ext/widgets/ColorButton.py
pyqt_ext/widgets/FlowLayout.py
pyqt_ext/widgets/MultiValueSpinBox.py
pyqt_ext/widgets/TableWidgetWithCopyPaste.py
pyqt_ext/widgets/__init__.py
pyqt_ext-2025.11.12.dist-info/WHEEL
pyqt_ext-2025.11.12.dist-info/METADATA
pyqt_ext-2025.11.12.dist-info/RECORD
