Metadata-Version: 2.3
Name: pyqt-ext
Version: 2025.11.12
Summary: Collection of PyQt widgets/tools
Keywords: PyQt,PySide,pyqtgraph
Author: Marcel Goldschen-Ohm
Author-email: Marcel Goldschen-Ohm <goldschen-ohm@utexas.edu>
Classifier: Development Status :: 4 - Beta
Classifier: Intended Audience :: Developers
Classifier: License :: OSI Approved :: MIT License
Classifier: Programming Language :: Python :: 3 :: Only
Requires-Dist: numpy
Requires-Dist: qtpy
Requires-Dist: qtawesome
Requires-Dist: pyqtgraph
Requires-Python: >=3.10
Project-URL: homepage, https://github.com/marcel-goldschen-ohm/pyqt-ext
Project-URL: issues, https://github.com/marcel-goldschen-ohm/pyqt-ext/issues
Project-URL: repository, https://github.com/marcel-goldschen-ohm/pyqt-ext
